.hgignore
.hgtags
README
setup.py
buildout/__init__.py
buildout.autoextras.egg-info/PKG-INFO
buildout.autoextras.egg-info/SOURCES.txt
buildout.autoextras.egg-info/dependency_links.txt
buildout.autoextras.egg-info/entry_points.txt
buildout.autoextras.egg-info/not-zip-safe
buildout.autoextras.egg-info/requires.txt
buildout.autoextras.egg-info/top_level.txt
buildout/autoextras/__init__.py
buildout/autoextras/extension.py
buildout/autoextras/extension.txt
buildout/autoextras/tests.py
docs/changes.rst