Metadata-Version: 1.0
Name: buildout.autoextras
Version: 1.1
Summary: zc.buildout extension to automatically include requirement extras
Home-page: http://bitbucket.org/pumazi/buildout.autoextras
Author: Michael Mulich
Author-email: michael.mulich@gmail.com
License: GPL
Keywords: plone buildout
Platform: UNKNOWN
Classifier: Framework :: Plone
Classifier: Programming Language :: Python
Classifier: Intended Audience :: Developers
Classifier: Development Status :: 5 - Production/Stable
